<?xml version="1.0" encoding="UTF-8" ?>
<odoo>
        <record id="education_schedule_view_form" model="ir.ui.view">
            <field name="inherit_id" ref="education.education_schedule_view_form" />
            <field name="model">education.schedule</field>
            <field name="arch" type="xml">
                <sheet position="before">
                    <header>
                        <button name="button_generate_view_issues" type="object"
                                string="Generate/View issues" class="oe_highlight"/>
                    </header>
                </sheet>
            </field>
        </record>
</odoo>
